pylogcat/Level.py
pylogcat/Log.py
pylogcat/__init__.py
pylogcat-0.0.3.dist-info/LICENSE
pylogcat-0.0.3.dist-info/METADATA
pylogcat-0.0.3.dist-info/WHEEL
pylogcat-0.0.3.dist-info/top_level.txt
pylogcat-0.0.3.dist-info/RECORD
