Metadata-Version: 2.1
Name: pylogcat
Version: 0.0.3
Summary: An application log system similar to Android Logcat for Python
Home-page: https://github.com/ellingtonsu/PyLogcat
Author: Wei-Tsung Su
Author-email: ellington.su@gmail.com
License: UNKNOWN
Platform: UNKNOWN
Classifier: Programming Language :: Python :: 3
Classifier: License :: OSI Approved :: Apache Software License
Classifier: Operating System :: OS Independent
Requires-Dist: enum
